<annotation>
	<folder>MothsandButterflies</folder>
	<filename> 57.jpg</filename>
	<path>/Users/gautamdevchowdary/internship/objectdetection/moths/flower-recognition/dataset/train/MothsandButterflies/ 57.jpg</path>
	<source>
		<database>Unknown</database>
	</source>
	<size>
		<width>1024</width>
		<height>768</height>
		<depth>3</depth>
	</size>
	<segmented>0</segmented>
	<object>
		<name>butterfly</name>
		<pose>Unspecified</pose>
		<truncated>0</truncated>
		<difficult>0</difficult>
		<bndbox>
			<xmin>134</xmin>
			<ymin>90</ymin>
			<xmax>835</xmax>
			<ymax>601</ymax>
		</bndbox>
	</object>
</annotation>
